JSEStocks/__init__.py
JSEStocks-0.0.3.dist-info/LICENSE
JSEStocks-0.0.3.dist-info/METADATA
JSEStocks-0.0.3.dist-info/WHEEL
JSEStocks-0.0.3.dist-info/top_level.txt
JSEStocks-0.0.3.dist-info/RECORD
