Metadata-Version: 2.1
Name: JSEStocks
Version: 0.0.3
Summary: a module that returns all the stock data in JSE
Home-page: https://www.adgstudios.co.za
Author: Ashlin Darius Govindasamy
Author-email: adg@adgstudios.co.za
License: MIT
Platform: UNKNOWN
Classifier: Programming Language :: Python :: 3
Classifier: License :: OSI Approved :: MIT License
Classifier: Operating System :: OS Independent
Requires-Dist: numpy
Requires-Dist: yfinance
